{"skeleton":{"hash":"MmCRjlG/iSgI7K4Bt6E0ZmzmQCo","spine":"3.8.99","images":"../../擬音語/gion/images/","audio":"C:/Users/TAKPON/Dropbox/新生魔法少女コノハ/魔法少女コノハ/audio/se/"},"bones":[{"name":"root"},{"name":"gi01_pusi","parent":"root","x":0.92,"y":239.2,"color":"fe3535ff"},{"name":"gi05_jupu","parent":"root","x":202.34,"y":255.08,"color":"fe3535ff"},{"name":"gi06_jupu","parent":"root","x":-2.6,"y":380.25,"color":"fe3535ff"},{"name":"gi07_gupo","parent":"root","x":85.93,"y":277.38,"color":"fe3535ff"},{"name":"gi08_nupu","parent":"root","x":162.18,"y":430.81,"color":"fe3535ff"},{"name":"gi09_sawa","parent":"root","x":-240.93,"y":695.62,"color":"fe3535ff"},{"name":"gi12_gui","parent":"root","x":-243.48,"y":601.31,"color":"fe3535ff"},{"name":"to01","parent":"root","x":-329.13,"y":843.12},{"name":"to02","parent":"root","x":-256.79,"y":771.43}],"slots":[{"name":"gi12_gui","bone":"gi12_gui"},{"name":"gi09_sawa","bone":"gi09_sawa"},{"name":"gi08_nupu","bone":"gi08_nupu"},{"name":"gi07_gupo","bone":"gi07_gupo"},{"name":"gi06_jupu","bone":"gi06_jupu"},{"name":"gi05_jupu","bone":"gi05_jupu"},{"name":"gi01_pusi","bone":"gi01_pusi"},{"name":"to01","bone":"to01"},{"name":"to02","bone":"to02"}],"skins":[{"name":"default","attachments":{"gi01_pusi":{"gi01_pusi":{"x":-7.45,"y":0.29,"width":119,"height":99}},"gi05_jupu":{"gi05_jupu":{"x":3.1,"y":7.81,"width":98,"height":74}},"gi06_jupu":{"gi06_jupu":{"x":1.5,"y":2.07,"width":101,"height":81}},"gi07_gupo":{"gi07_gupo":{"x":2.75,"y":7.04,"width":81,"height":84}},"gi08_nupu":{"gi08_nupu":{"x":2.66,"y":-1.27,"width":99,"height":75}},"gi09_sawa":{"gi09_sawa":{"x":2.18,"y":-1.95,"width":82,"height":76}},"gi12_gui":{"gi12_gui":{"x":6.33,"y":2.56,"width":99,"height":89}},"to01":{"to01":{"x":-4.78,"y":-2.55,"width":107,"height":102}},"to02":{"to02":{"x":0.73,"y":1.41,"width":100,"height":93}}}}],"events":{"H_chu01":{"audio":"H_chu01.ogg"},"H_chu03":{"audio":"H_chu03.ogg"},"H_chu05":{"audio":"H_chu05.ogg"},"H_chu06":{"audio":"H_chu06.ogg"},"H_gui":{"audio":"H_gui.ogg"},"H_gyu":{"audio":"H_gyu.ogg"},"H_kyun":{"audio":"H_kyun.ogg"},"H_pis01":{"audio":"H_pis01.ogg"},"H_pis02":{"audio":"H_pis02.ogg"},"H_pis03":{"audio":"H_pis03.ogg"},"H_pis05":{"audio":"H_pis05.ogg"},"H_siohuki":{"audio":"H_siohuki.ogg"},"H_siru01":{"audio":"H_siru01.ogg"},"H_syasei01":{"audio":"H_syasei01.ogg"},"H_syasei02":{"audio":"H_syasei02.ogg"},"H_syasei03":{"audio":"H_syasei03.ogg"},"H_syasei05":{"audio":"H_syasei05.ogg"},"H_syasei06":{"audio":"H_syasei06.ogg"},"H_touch":{"audio":"H_touch.ogg"},"H_warm":{"audio":"H_warm.ogg"},"H_zukin":{"audio":"H_zukin.ogg"},"H_zukun":{"audio":"H_zukun.ogg"},"SC_heartbeat":{"audio":"SC_heartbeat.ogg"}},"animations":{"ero1":{"slots":{"gi05_jupu":{"color":[{"color":"ffffff00","curve":"stepped"},{"time":1,"color":"ffffff00","curve":0.271,"c2":-0.26,"c3":0.323,"c4":0.78},{"time":1.5,"color":"ffffffff","curve":"stepped"},{"time":2,"color":"ffffffff","curve":0.271,"c2":-0.26,"c3":0.323,"c4":0.78},{"time":2.1667,"color":"ffffff00"}],"attachment":[{"name":"gi05_jupu"},{"time":4,"name":"gi05_jupu"}]},"gi06_jupu":{"color":[{"color":"ffffff00","curve":"stepped"},{"time":0.1667,"color":"ffffff00"},{"time":0.6667,"color":"ffffffff","curve":"stepped"},{"time":1.1667,"color":"ffffffff"},{"time":1.3333,"color":"ffffff00"}],"attachment":[{"name":"gi06_jupu"}]},"gi08_nupu":{"color":[{"color":"ffffff00","curve":"stepped"},{"time":0.3333,"color":"ffffff00","curve":0.421,"c2":-0.35,"c3":0.519,"c4":0.89},{"time":0.8333,"color":"ffffffff","curve":"stepped"},{"time":1.3333,"color":"ffffffff","curve":0.421,"c2":-0.35,"c3":0.519,"c4":0.89},{"time":1.5,"color":"ffffff00"}],"attachment":[{"name":"gi08_nupu"}]},"gi12_gui":{"color":[{"color":"ffffff00","curve":"stepped"},{"time":0.6667,"color":"ffffff00","curve":0.299,"c2":-0.14,"c3":0.589,"c4":0.89},{"time":1.1667,"color":"ffffffff","curve":"stepped"},{"time":1.6667,"color":"ffffffff","curve":0.299,"c2":-0.14,"c3":0.589,"c4":0.89},{"time":1.8333,"color":"ffffff00"}],"attachment":[{"name":"gi12_gui"}]}},"bones":{"gi12_gui":{"translate":[{"time":0.6667,"curve":0.299,"c2":-0.14,"c3":0.589,"c4":0.89},{"time":1.1667,"x":2.43,"curve":0.331,"c2":-0.27,"c3":0.659,"c4":0.21},{"time":1.3333,"x":-0.11,"y":0.07,"curve":0.293,"c2":0.33,"c3":0.608,"c4":0.91},{"time":1.6667,"x":6.08,"y":0.3,"curve":0.299,"c2":-0.14,"c3":0.589,"c4":0.89},{"time":1.8333,"x":12.46,"y":-0.3}],"scale":[{"x":0.001,"y":0.001,"curve":"stepped"},{"time":0.6667,"x":0.001,"y":0.001,"curve":0.299,"c2":-0.14,"c3":0.589,"c4":0.89},{"time":1.1667,"curve":0.299,"c2":-0.14,"c3":0.589,"c4":0.89},{"time":1.6667,"x":1.1}]},"gi08_nupu":{"translate":[{"time":0.8333,"curve":0.421,"c2":-0.35,"c3":0.519,"c4":0.89},{"time":1,"x":-0.59,"y":7.71,"curve":0.421,"c2":-0.35,"c3":0.519,"c4":0.89},{"time":1.1667,"x":-0.59,"y":3.56,"curve":0.421,"c2":-0.35,"c3":0.519,"c4":0.89},{"time":1.3333,"x":-0.59,"y":1.19}],"scale":[{"x":0.001,"y":0.001,"curve":"stepped"},{"time":0.3333,"x":0.001,"y":0.001,"curve":0.421,"c2":-0.35,"c3":0.519,"c4":0.89},{"time":0.8333,"curve":0.421,"c2":-0.35,"c3":0.519,"c4":0.89},{"time":1.3333,"x":1.1,"y":1.1}]},"gi06_jupu":{"translate":[{"time":0.6667},{"time":1.1667,"x":-0.89,"y":7.99}],"scale":[{"x":0.001,"y":0.001,"curve":"stepped"},{"time":0.1667,"x":0.001,"y":0.001},{"time":0.6667},{"time":1.1667,"x":1.1,"y":1.1}]},"gi05_jupu":{"translate":[{"time":1.5,"curve":0.271,"c2":-0.26,"c3":0.323,"c4":0.78},{"time":2,"x":-0.33,"y":5.26}],"scale":[{"x":0.001,"y":0.001,"curve":"stepped"},{"time":1,"x":0.001,"y":0.001,"curve":0.271,"c2":-0.26,"c3":0.323,"c4":0.78},{"time":1.5},{"time":2,"x":1.1,"y":1.1}]}},"events":[{"time":0.6667,"name":"H_chu03"},{"time":0.6667,"name":"H_chu05","balance":0.57},{"time":1.1667,"name":"H_gui","volume":0.29,"balance":-0.72},{"time":1.5,"name":"H_chu01"}]},"ero2":{"slots":{"gi05_jupu":{"color":[{"color":"ffffff00","curve":"stepped"},{"time":1,"color":"ffffff00","curve":0.271,"c2":-0.26,"c3":0.323,"c4":0.78},{"time":1.5,"color":"ffffffff","curve":"stepped"},{"time":2,"color":"ffffffff","curve":0.271,"c2":-0.26,"c3":0.323,"c4":0.78},{"time":2.1667,"color":"ffffff00"}],"attachment":[{"name":"gi05_jupu"},{"time":4,"name":"gi05_jupu"}]},"gi06_jupu":{"color":[{"color":"ffffff00","curve":"stepped"},{"time":0.1667,"color":"ffffff00"},{"time":0.6667,"color":"ffffffff","curve":"stepped"},{"time":1.1667,"color":"ffffffff"},{"time":1.3333,"color":"ffffff00","curve":"stepped"},{"time":2.1,"color":"ffffff00"},{"time":2.6,"color":"ffffffff","curve":"stepped"},{"time":3.1,"color":"ffffffff"},{"time":3.2667,"color":"ffffff00"}],"attachment":[{"name":"gi06_jupu"}]},"gi08_nupu":{"color":[{"color":"ffffff00","curve":"stepped"},{"time":2.3333,"color":"ffffff00","curve":0.421,"c2":-0.35,"c3":0.519,"c4":0.89},{"time":2.8333,"color":"ffffffff","curve":"stepped"},{"time":3.3333,"color":"ffffffff","curve":0.421,"c2":-0.35,"c3":0.519,"c4":0.89},{"time":3.5,"color":"ffffff00"}],"attachment":[{"name":"gi08_nupu"}]},"gi12_gui":{"color":[{"color":"ffffff00","curve":"stepped"},{"time":2,"color":"ffffff00","curve":0.299,"c2":-0.14,"c3":0.589,"c4":0.89},{"time":2.5,"color":"ffffffff","curve":"stepped"},{"time":3,"color":"ffffffff","curve":0.299,"c2":-0.14,"c3":0.589,"c4":0.89},{"time":3.1667,"color":"ffffff00"}],"attachment":[{"name":"gi12_gui"}]}},"bones":{"gi12_gui":{"translate":[{"time":2,"curve":0.299,"c2":-0.14,"c3":0.589,"c4":0.89},{"time":2.5,"x":2.43,"curve":0.331,"c2":-0.27,"c3":0.659,"c4":0.21},{"time":2.6667,"x":-0.11,"y":0.07,"curve":0.293,"c2":0.33,"c3":0.608,"c4":0.91},{"time":3,"x":6.08,"y":0.3,"curve":0.299,"c2":-0.14,"c3":0.589,"c4":0.89},{"time":3.1667,"x":12.46,"y":-0.3}],"scale":[{"x":0.001,"y":0.001,"curve":"stepped"},{"time":2,"x":0.001,"y":0.001,"curve":0.299,"c2":-0.14,"c3":0.589,"c4":0.89},{"time":2.5,"curve":0.299,"c2":-0.14,"c3":0.589,"c4":0.89},{"time":3,"x":1.1}]},"gi08_nupu":{"translate":[{"time":2.8333,"curve":0.421,"c2":-0.35,"c3":0.519,"c4":0.89},{"time":3,"x":-0.59,"y":7.71,"curve":0.421,"c2":-0.35,"c3":0.519,"c4":0.89},{"time":3.1667,"x":-0.59,"y":3.56,"curve":0.421,"c2":-0.35,"c3":0.519,"c4":0.89},{"time":3.3333,"x":-0.59,"y":1.19}],"scale":[{"x":0.001,"y":0.001,"curve":"stepped"},{"time":2.3333,"x":0.001,"y":0.001,"curve":0.421,"c2":-0.35,"c3":0.519,"c4":0.89},{"time":2.8333,"curve":0.421,"c2":-0.35,"c3":0.519,"c4":0.89},{"time":3.3333,"x":1.1,"y":1.1}]},"gi06_jupu":{"translate":[{"time":0.6667},{"time":1.1667,"x":-0.89,"y":7.99},{"time":2.1,"curve":"stepped"},{"time":2.6},{"time":3.1,"x":-0.89,"y":7.99}],"scale":[{"x":0.001,"y":0.001,"curve":"stepped"},{"time":0.1667,"x":0.001,"y":0.001},{"time":0.6667},{"time":1.1667,"x":1.1,"y":1.1},{"time":2.1,"x":0.001,"y":0.001},{"time":2.6},{"time":3.1,"x":1.1,"y":1.1}]},"gi05_jupu":{"translate":[{"time":1.5,"curve":0.271,"c2":-0.26,"c3":0.323,"c4":0.78},{"time":2,"x":-0.33,"y":5.26}],"scale":[{"x":0.001,"y":0.001,"curve":"stepped"},{"time":1,"x":0.001,"y":0.001,"curve":0.271,"c2":-0.26,"c3":0.323,"c4":0.78},{"time":1.5},{"time":2,"x":1.1,"y":1.1}]}},"events":[{"time":0.6667,"name":"H_chu03"},{"time":1.5,"name":"H_chu01"},{"time":2.5,"name":"H_gui","volume":0.29,"balance":-0.72},{"time":2.6,"name":"H_chu03"},{"time":2.6667,"name":"H_chu05","balance":0.57}]},"ero3":{"slots":{"gi05_jupu":{"color":[{"color":"ffffff00","curve":"stepped"},{"time":1,"color":"ffffff00","curve":0.271,"c2":-0.26,"c3":0.323,"c4":0.78},{"time":1.5,"color":"ffffffff","curve":"stepped"},{"time":2,"color":"ffffffff","curve":0.271,"c2":-0.26,"c3":0.323,"c4":0.78},{"time":2.1667,"color":"ffffff00"}],"attachment":[{"name":"gi05_jupu"}]},"gi06_jupu":{"color":[{"color":"ffffff00","curve":"stepped"},{"time":0.1667,"color":"ffffff00"},{"time":0.6667,"color":"ffffffff","curve":"stepped"},{"time":1.1667,"color":"ffffffff"},{"time":1.3333,"color":"ffffff00","curve":"stepped"},{"time":2.1,"color":"ffffff00"},{"time":2.6,"color":"ffffffff","curve":"stepped"},{"time":3.1,"color":"ffffffff"},{"time":3.2667,"color":"ffffff00"}],"attachment":[{"name":"gi06_jupu"}]},"gi07_gupo":{"color":[{"color":"ffffff00","curve":"stepped"},{"time":2,"color":"ffffff00","curve":0.344,"c2":-0.29,"c3":0.526,"c4":-0.08},{"time":2.5,"color":"ffffffff","curve":"stepped"},{"time":3,"color":"ffffffff","curve":0.344,"c2":-0.29,"c3":0.526,"c4":-0.08},{"time":3.1667,"color":"ffffff00"}],"attachment":[{"name":"gi07_gupo"}]},"gi08_nupu":{"color":[{"color":"ffffff00","curve":"stepped"},{"time":2.3333,"color":"ffffff00","curve":0.421,"c2":-0.35,"c3":0.519,"c4":0.89},{"time":2.8333,"color":"ffffffff","curve":"stepped"},{"time":3.3333,"color":"ffffffff","curve":0.421,"c2":-0.35,"c3":0.519,"c4":0.89},{"time":3.5,"color":"ffffff00"}],"attachment":[{"name":"gi08_nupu"}]},"gi12_gui":{"color":[{"color":"ffffff00","curve":"stepped"},{"time":0.3333,"color":"ffffff00","curve":0.299,"c2":-0.14,"c3":0.589,"c4":0.89},{"time":0.8333,"color":"ffffffff","curve":"stepped"},{"time":1.3333,"color":"ffffffff","curve":0.299,"c2":-0.14,"c3":0.589,"c4":0.89},{"time":1.5,"color":"ffffff00"}],"attachment":[{"name":"gi12_gui"}]},"to01":{"color":[{"color":"ffffff00","curve":"stepped"},{"time":2,"color":"ffffff00"},{"time":2.5,"color":"ffffffff"},{"time":4,"color":"ffffff00"}],"attachment":[{"name":"to01"}]},"to02":{"color":[{"color":"ffffff00","curve":"stepped"},{"time":1,"color":"ffffff00"},{"time":1.5,"color":"ffffffff"},{"time":3,"color":"ffffff00"}],"attachment":[{"name":"to02"}]}},"bones":{"to02":{"translate":[{"time":1},{"time":1.5,"x":-12.42,"y":-4.83},{"time":3,"x":-20.01,"y":-7.59}],"scale":[{"time":1},{"time":1.5,"x":1.2,"y":1.2},{"time":3,"x":1.3,"y":1.3}]},"to01":{"translate":[{"time":2},{"time":2.5,"x":-11.73,"y":5.52},{"time":4,"x":-19.32,"y":8.28}],"scale":[{"time":2},{"time":2.5,"x":1.2,"y":1.2},{"time":4,"x":1.3,"y":1.3}]},"gi12_gui":{"translate":[{"time":0.3333,"curve":0.299,"c2":-0.14,"c3":0.589,"c4":0.89},{"time":0.8333,"x":2.43,"curve":0.331,"c2":-0.27,"c3":0.659,"c4":0.21},{"time":1,"x":-0.11,"y":0.07,"curve":0.293,"c2":0.33,"c3":0.608,"c4":0.91},{"time":1.3333,"x":6.08,"y":0.3,"curve":0.299,"c2":-0.14,"c3":0.589,"c4":0.89},{"time":1.5,"x":12.46,"y":-0.3}],"scale":[{"x":0.001,"y":0.001,"curve":"stepped"},{"time":0.3333,"x":0.001,"y":0.001,"curve":0.299,"c2":-0.14,"c3":0.589,"c4":0.89},{"time":0.8333,"curve":0.299,"c2":-0.14,"c3":0.589,"c4":0.89},{"time":1.3333,"x":1.1}]},"gi08_nupu":{"translate":[{"time":2.8333,"curve":0.421,"c2":-0.35,"c3":0.519,"c4":0.89},{"time":3,"x":-0.59,"y":7.71,"curve":0.421,"c2":-0.35,"c3":0.519,"c4":0.89},{"time":3.1667,"x":-0.59,"y":3.56,"curve":0.421,"c2":-0.35,"c3":0.519,"c4":0.89},{"time":3.3333,"x":-0.59,"y":1.19}],"scale":[{"x":0.001,"y":0.001,"curve":"stepped"},{"time":2.3333,"x":0.001,"y":0.001,"curve":0.421,"c2":-0.35,"c3":0.519,"c4":0.89},{"time":2.8333,"curve":0.421,"c2":-0.35,"c3":0.519,"c4":0.89},{"time":3.3333,"x":1.1,"y":1.1}]},"gi07_gupo":{"translate":[{"time":2.5,"curve":0.344,"c2":-0.29,"c3":0.495,"c4":0.38},{"time":3,"y":5.69}],"scale":[{"x":0.001,"y":0.001,"curve":"stepped"},{"time":2,"x":0.001,"y":0.001},{"time":2.5},{"time":3,"x":1.1,"y":1.1}]},"gi06_jupu":{"translate":[{"time":0.6667},{"time":1.1667,"x":-0.89,"y":7.99},{"time":2.1,"curve":"stepped"},{"time":2.6},{"time":3.1,"x":-0.89,"y":7.99}],"scale":[{"x":0.001,"y":0.001,"curve":"stepped"},{"time":0.1667,"x":0.001,"y":0.001},{"time":0.6667},{"time":1.1667,"x":1.1,"y":1.1},{"time":2.1,"x":0.001,"y":0.001},{"time":2.6},{"time":3.1,"x":1.1,"y":1.1}]},"gi05_jupu":{"translate":[{"time":1.5,"curve":0.271,"c2":-0.26,"c3":0.323,"c4":0.78},{"time":2,"x":-0.33,"y":5.26}],"scale":[{"x":0.001,"y":0.001,"curve":"stepped"},{"time":1,"x":0.001,"y":0.001,"curve":0.271,"c2":-0.26,"c3":0.323,"c4":0.78},{"time":1.5},{"time":2,"x":1.1,"y":1.1}]}},"events":[{"time":0.6667,"name":"H_chu03"},{"time":0.8333,"name":"H_gui","volume":0.29,"balance":-0.72},{"time":1.5,"name":"H_chu01"},{"time":2,"name":"H_syasei03"},{"time":2.6,"name":"H_chu03"},{"time":2.6667,"name":"H_chu05","balance":0.57}]},"ero4":{"slots":{"gi01_pusi":{"color":[{"color":"ffffff00","curve":"stepped"},{"time":2.3333,"color":"ffffff00","curve":0.281,"c2":-0.51,"c3":0.379,"c4":0.88},{"time":2.8333,"color":"ffffffff","curve":"stepped"},{"time":3.3333,"color":"ffffffff","curve":0.281,"c2":-0.51,"c3":0.379,"c4":0.88},{"time":3.5,"color":"ffffff00"}],"attachment":[{"name":"gi01_pusi"}]},"gi05_jupu":{"color":[{"color":"ffffff00","curve":"stepped"},{"time":1,"color":"ffffff00","curve":0.271,"c2":-0.26,"c3":0.323,"c4":0.78},{"time":1.5,"color":"ffffffff","curve":"stepped"},{"time":2,"color":"ffffffff","curve":0.271,"c2":-0.26,"c3":0.323,"c4":0.78},{"time":2.1667,"color":"ffffff00"}],"attachment":[{"name":"gi05_jupu"}]},"gi06_jupu":{"color":[{"color":"ffffff00","curve":"stepped"},{"time":0.1667,"color":"ffffff00"},{"time":0.6667,"color":"ffffffff","curve":"stepped"},{"time":1.1667,"color":"ffffffff"},{"time":1.3333,"color":"ffffff00","curve":"stepped"},{"time":2.1,"color":"ffffff00"},{"time":2.6,"color":"ffffffff","curve":"stepped"},{"time":3.1,"color":"ffffffff"},{"time":3.2667,"color":"ffffff00"}],"attachment":[{"name":"gi06_jupu"}]},"gi07_gupo":{"color":[{"color":"ffffff00","curve":"stepped"},{"time":2,"color":"ffffff00","curve":0.344,"c2":-0.29,"c3":0.526,"c4":-0.08},{"time":2.5,"color":"ffffffff","curve":"stepped"},{"time":3,"color":"ffffffff","curve":0.344,"c2":-0.29,"c3":0.526,"c4":-0.08},{"time":3.1667,"color":"ffffff00"}],"attachment":[{"name":"gi07_gupo"}]},"gi08_nupu":{"color":[{"color":"ffffff00","curve":"stepped"},{"time":2.3333,"color":"ffffff00","curve":0.421,"c2":-0.35,"c3":0.519,"c4":0.89},{"time":2.8333,"color":"ffffffff","curve":"stepped"},{"time":3.3333,"color":"ffffffff","curve":0.421,"c2":-0.35,"c3":0.519,"c4":0.89},{"time":3.5,"color":"ffffff00"}],"attachment":[{"name":"gi08_nupu"}]},"gi12_gui":{"color":[{"color":"ffffff00","curve":"stepped"},{"time":0.3333,"color":"ffffff00","curve":0.299,"c2":-0.14,"c3":0.589,"c4":0.89},{"time":0.8333,"color":"ffffffff","curve":"stepped"},{"time":1.3333,"color":"ffffffff","curve":0.299,"c2":-0.14,"c3":0.589,"c4":0.89},{"time":1.5,"color":"ffffff00"}],"attachment":[{"name":"gi12_gui"}]},"to01":{"color":[{"color":"ffffff00","curve":"stepped"},{"time":2,"color":"ffffff00"},{"time":2.5,"color":"ffffffff"},{"time":4,"color":"ffffff00"}],"attachment":[{"name":"to01"}]},"to02":{"color":[{"color":"ffffff00","curve":"stepped"},{"time":1,"color":"ffffff00"},{"time":1.5,"color":"ffffffff"},{"time":3,"color":"ffffff00"}],"attachment":[{"name":"to02"}]}},"bones":{"to02":{"translate":[{"time":1},{"time":1.5,"x":-12.42,"y":-4.83},{"time":3,"x":-20.01,"y":-7.59}],"scale":[{"time":1},{"time":1.5,"x":1.2,"y":1.2},{"time":3,"x":1.3,"y":1.3}]},"to01":{"translate":[{"time":2},{"time":2.5,"x":-11.73,"y":5.52},{"time":4,"x":-19.32,"y":8.28}],"scale":[{"time":2},{"time":2.5,"x":1.2,"y":1.2},{"time":4,"x":1.3,"y":1.3}]},"gi12_gui":{"translate":[{"time":0.3333,"curve":0.299,"c2":-0.14,"c3":0.589,"c4":0.89},{"time":0.8333,"x":2.43,"curve":0.331,"c2":-0.27,"c3":0.659,"c4":0.21},{"time":1,"x":-0.11,"y":0.07,"curve":0.293,"c2":0.33,"c3":0.608,"c4":0.91},{"time":1.3333,"x":6.08,"y":0.3,"curve":0.299,"c2":-0.14,"c3":0.589,"c4":0.89},{"time":1.5,"x":12.46,"y":-0.3}],"scale":[{"x":0.001,"y":0.001,"curve":"stepped"},{"time":0.3333,"x":0.001,"y":0.001,"curve":0.299,"c2":-0.14,"c3":0.589,"c4":0.89},{"time":0.8333,"curve":0.299,"c2":-0.14,"c3":0.589,"c4":0.89},{"time":1.3333,"x":1.1}]},"gi08_nupu":{"translate":[{"time":2.8333,"curve":0.421,"c2":-0.35,"c3":0.519,"c4":0.89},{"time":3,"x":-0.59,"y":7.71,"curve":0.421,"c2":-0.35,"c3":0.519,"c4":0.89},{"time":3.1667,"x":-0.59,"y":3.56,"curve":0.421,"c2":-0.35,"c3":0.519,"c4":0.89},{"time":3.3333,"x":-0.59,"y":1.19}],"scale":[{"x":0.001,"y":0.001,"curve":"stepped"},{"time":2.3333,"x":0.001,"y":0.001,"curve":0.421,"c2":-0.35,"c3":0.519,"c4":0.89},{"time":2.8333,"curve":0.421,"c2":-0.35,"c3":0.519,"c4":0.89},{"time":3.3333,"x":1.1,"y":1.1}]},"gi07_gupo":{"translate":[{"time":2.5,"curve":0.344,"c2":-0.29,"c3":0.495,"c4":0.38},{"time":3,"y":5.69}],"scale":[{"x":0.001,"y":0.001,"curve":"stepped"},{"time":2,"x":0.001,"y":0.001},{"time":2.5},{"time":3,"x":1.1,"y":1.1}]},"gi06_jupu":{"translate":[{"time":0.6667},{"time":1.1667,"x":-0.89,"y":7.99},{"time":2.1,"curve":"stepped"},{"time":2.6},{"time":3.1,"x":-0.89,"y":7.99}],"scale":[{"x":0.001,"y":0.001,"curve":"stepped"},{"time":0.1667,"x":0.001,"y":0.001},{"time":0.6667},{"time":1.1667,"x":1.1,"y":1.1},{"time":2.1,"x":0.001,"y":0.001},{"time":2.6},{"time":3.1,"x":1.1,"y":1.1}]},"gi05_jupu":{"translate":[{"time":1.5,"curve":0.271,"c2":-0.26,"c3":0.323,"c4":0.78},{"time":2,"x":-0.33,"y":5.26}],"scale":[{"x":0.001,"y":0.001,"curve":"stepped"},{"time":1,"x":0.001,"y":0.001,"curve":0.271,"c2":-0.26,"c3":0.323,"c4":0.78},{"time":1.5},{"time":2,"x":1.1,"y":1.1}]},"gi01_pusi":{"translate":[{"time":2.8333,"curve":0.281,"c2":-0.51,"c3":0.379,"c4":0.88},{"time":2.8667,"x":1.89,"y":0.38,"curve":0.281,"c2":-0.51,"c3":0.379,"c4":0.88},{"time":2.9,"curve":0.281,"c2":-0.51,"c3":0.379,"c4":0.88},{"time":2.9333,"x":-4.52,"curve":0.281,"c2":-0.51,"c3":0.379,"c4":0.88},{"time":2.9667,"curve":0.281,"c2":-0.51,"c3":0.379,"c4":0.88},{"time":3,"x":1.89,"y":0.38,"curve":0.281,"c2":-0.51,"c3":0.379,"c4":0.88},{"time":3.0333,"curve":0.281,"c2":-0.51,"c3":0.379,"c4":0.88},{"time":3.0667,"x":-4.52,"curve":0.281,"c2":-0.51,"c3":0.379,"c4":0.88},{"time":3.1,"curve":0.281,"c2":-0.51,"c3":0.379,"c4":0.88},{"time":3.1333,"x":1.89,"y":0.38,"curve":0.281,"c2":-0.51,"c3":0.379,"c4":0.88},{"time":3.1667,"curve":0.281,"c2":-0.51,"c3":0.379,"c4":0.88},{"time":3.2,"x":-4.52}],"scale":[{"x":0.001,"y":0.001,"curve":"stepped"},{"time":2.3333,"x":0.001,"y":0.001,"curve":0.281,"c2":-0.51,"c3":0.379,"c4":0.88},{"time":2.8333,"curve":0.281,"c2":-0.51,"c3":0.379,"c4":0.88},{"time":3.3333,"x":1.1,"y":1.1}]}},"events":[{"time":0.6667,"name":"H_chu03"},{"time":0.8333,"name":"H_gui","volume":0.29,"balance":-0.72},{"time":1.5,"name":"H_chu01"},{"time":2.5,"name":"H_siohuki"},{"time":2.6,"name":"H_chu03"},{"time":2.6667,"name":"H_chu05","balance":0.57}]},"gui":{"slots":{"gi12_gui":{"color":[{"color":"ffffff00","curve":0.299,"c2":-0.14,"c3":0.589,"c4":0.89},{"time":0.5,"color":"ffffffff","curve":"stepped"},{"time":1,"color":"ffffffff","curve":0.299,"c2":-0.14,"c3":0.589,"c4":0.89},{"time":1.1667,"color":"ffffff00"}],"attachment":[{"name":"gi12_gui"}]}},"bones":{"gi12_gui":{"translate":[{"curve":0.299,"c2":-0.14,"c3":0.589,"c4":0.89},{"time":0.5,"x":2.43,"curve":0.331,"c2":-0.27,"c3":0.659,"c4":0.21},{"time":0.6667,"x":-0.11,"y":0.07,"curve":0.293,"c2":0.33,"c3":0.608,"c4":0.91},{"time":1,"x":6.08,"y":0.3,"curve":0.299,"c2":-0.14,"c3":0.589,"c4":0.89},{"time":1.1667,"x":12.46,"y":-0.3}],"scale":[{"x":0.001,"y":0.001,"curve":0.299,"c2":-0.14,"c3":0.589,"c4":0.89},{"time":0.5,"curve":0.299,"c2":-0.14,"c3":0.589,"c4":0.89},{"time":1,"x":1.1}]}},"events":[{"time":0.5,"name":"H_gui","volume":0.83,"balance":0.47}]},"gupo":{"slots":{"gi07_gupo":{"color":[{"color":"ffffff00","curve":0.344,"c2":-0.29,"c3":0.526,"c4":-0.08},{"time":0.5,"color":"ffffffff","curve":"stepped"},{"time":1,"color":"ffffffff","curve":0.344,"c2":-0.29,"c3":0.526,"c4":-0.08},{"time":1.1667,"color":"ffffff00"}],"attachment":[{"name":"gi07_gupo"}]}},"bones":{"gi07_gupo":{"translate":[{"time":0.5,"curve":0.344,"c2":-0.29,"c3":0.495,"c4":0.38},{"time":1,"y":5.69}],"scale":[{"x":0.001,"y":0.001},{"time":0.5},{"time":1,"x":1.1,"y":1.1}]}},"events":[{"name":"H_syasei03"}]},"jupu":{"slots":{"gi05_jupu":{"color":[{"color":"ffffff00","curve":0.271,"c2":-0.26,"c3":0.323,"c4":0.78},{"time":0.5,"color":"ffffffff","curve":"stepped"},{"time":1,"color":"ffffffff","curve":0.271,"c2":-0.26,"c3":0.323,"c4":0.78},{"time":1.1667,"color":"ffffff00"}],"attachment":[{"name":"gi05_jupu"}]}},"bones":{"gi05_jupu":{"translate":[{"time":0.5,"curve":0.271,"c2":-0.26,"c3":0.323,"c4":0.78},{"time":1,"x":-0.33,"y":5.26}],"scale":[{"x":0.001,"y":0.001,"curve":0.271,"c2":-0.26,"c3":0.323,"c4":0.78},{"time":0.5},{"time":1,"x":1.1,"y":1.1}]}},"events":[{"time":0.5,"name":"H_chu01"}]},"jupu2":{"slots":{"gi06_jupu":{"color":[{"color":"ffffff00"},{"time":0.5,"color":"ffffffff","curve":"stepped"},{"time":1,"color":"ffffffff"},{"time":1.1667,"color":"ffffff00"}],"attachment":[{"name":"gi06_jupu"}]}},"bones":{"gi06_jupu":{"translate":[{"time":0.5},{"time":1,"x":-0.89,"y":7.99}],"scale":[{"x":0.001,"y":0.001},{"time":0.5},{"time":1,"x":1.1,"y":1.1}]}},"events":[{"time":0.5,"name":"H_chu03"}]},"nupu":{"slots":{"gi08_nupu":{"color":[{"color":"ffffff00","curve":0.421,"c2":-0.35,"c3":0.519,"c4":0.89},{"time":0.5,"color":"ffffffff","curve":"stepped"},{"time":1,"color":"ffffffff","curve":0.421,"c2":-0.35,"c3":0.519,"c4":0.89},{"time":1.1667,"color":"ffffff00"}],"attachment":[{"name":"gi08_nupu"}]}},"bones":{"gi08_nupu":{"translate":[{"time":0.5,"curve":0.421,"c2":-0.35,"c3":0.519,"c4":0.89},{"time":0.6667,"x":-0.59,"y":7.71,"curve":0.421,"c2":-0.35,"c3":0.519,"c4":0.89},{"time":0.8333,"x":-0.59,"y":3.56,"curve":0.421,"c2":-0.35,"c3":0.519,"c4":0.89},{"time":1,"x":-0.59,"y":1.19}],"scale":[{"x":0.001,"y":0.001,"curve":0.421,"c2":-0.35,"c3":0.519,"c4":0.89},{"time":0.5,"curve":0.421,"c2":-0.35,"c3":0.519,"c4":0.89},{"time":1,"x":1.1,"y":1.1}]}},"events":[{"time":0.5,"name":"H_chu05","balance":0.57}]},"pusi":{"slots":{"gi01_pusi":{"color":[{"color":"ffffff00","curve":0.281,"c2":-0.51,"c3":0.379,"c4":0.88},{"time":0.5,"color":"ffffffff","curve":"stepped"},{"time":1,"color":"ffffffff","curve":0.281,"c2":-0.51,"c3":0.379,"c4":0.88},{"time":1.1667,"color":"ffffff00"}],"attachment":[{"name":"gi01_pusi"}]}},"bones":{"gi01_pusi":{"translate":[{"time":0.5,"curve":0.281,"c2":-0.51,"c3":0.379,"c4":0.88},{"time":0.5333,"x":1.89,"y":0.38,"curve":0.281,"c2":-0.51,"c3":0.379,"c4":0.88},{"time":0.5667,"curve":0.281,"c2":-0.51,"c3":0.379,"c4":0.88},{"time":0.6,"x":-4.52,"curve":0.281,"c2":-0.51,"c3":0.379,"c4":0.88},{"time":0.6333,"curve":0.281,"c2":-0.51,"c3":0.379,"c4":0.88},{"time":0.6667,"x":1.89,"y":0.38,"curve":0.281,"c2":-0.51,"c3":0.379,"c4":0.88},{"time":0.7,"curve":0.281,"c2":-0.51,"c3":0.379,"c4":0.88},{"time":0.7333,"x":-4.52,"curve":0.281,"c2":-0.51,"c3":0.379,"c4":0.88},{"time":0.7667,"curve":0.281,"c2":-0.51,"c3":0.379,"c4":0.88},{"time":0.8,"x":1.89,"y":0.38,"curve":0.281,"c2":-0.51,"c3":0.379,"c4":0.88},{"time":0.8333,"curve":0.281,"c2":-0.51,"c3":0.379,"c4":0.88},{"time":0.8667,"x":-4.52}],"scale":[{"x":0.001,"y":0.001,"curve":0.281,"c2":-0.51,"c3":0.379,"c4":0.88},{"time":0.5,"curve":0.281,"c2":-0.51,"c3":0.379,"c4":0.88},{"time":1,"x":1.1,"y":1.1}]}},"events":[{"time":0.1667,"name":"H_siohuki"}]},"sawa":{"slots":{"gi09_sawa":{"color":[{"color":"ffffff00","curve":0.379,"c2":-0.39,"c3":0.75},{"time":0.5,"color":"ffffffff","curve":"stepped"},{"time":1,"color":"ffffffff","curve":0.379,"c2":-0.39,"c3":0.75},{"time":1.1667,"color":"ffffff00"}],"attachment":[{"name":"gi09_sawa"}]}},"bones":{"gi09_sawa":{"translate":[{"time":0.5,"curve":0.379,"c2":-0.39,"c3":0.75},{"time":0.6,"x":-0.54,"y":5.96,"curve":0.379,"c2":-0.39,"c3":0.75},{"time":0.7,"x":-4.07,"y":5.96,"curve":0.379,"c2":-0.39,"c3":0.75},{"time":0.8,"x":-0.54,"y":5.96,"curve":0.379,"c2":-0.39,"c3":0.75},{"time":0.9,"x":1.9,"y":6.23,"curve":0.379,"c2":-0.39,"c3":0.75},{"time":1,"x":-0.54,"y":5.96}],"scale":[{"x":0.001,"y":0.001,"curve":0.379,"c2":-0.39,"c3":0.75},{"time":0.5,"curve":0.379,"c2":-0.39,"c3":0.75},{"time":1,"x":1.1,"y":1.1}]}},"events":[{"time":0.5,"name":"H_touch","volume":0.23,"balance":-0.1}]},"to01":{"slots":{"to01":{"color":[{"color":"ffffff00"},{"time":0.5,"color":"ffffffff"},{"time":2,"color":"ffffff00"}],"attachment":[{"name":"to01"}]}},"bones":{"to01":{"scale":[{},{"time":0.5,"x":1.2,"y":1.2},{"time":2,"x":1.3,"y":1.3}]},"to02":{"scale":[{},{"time":0.5,"x":1.2,"y":1.2},{"time":2,"x":1.3,"y":1.3}]}}},"to02":{"slots":{"to01":{"color":[{"color":"ffffff00"},{"time":0.5,"color":"ffffffff"},{"time":2,"color":"ffffff00"}]},"to02":{"color":[{"color":"ffffff00"},{"time":0.5,"color":"ffffffff"},{"time":2,"color":"ffffff00"}],"attachment":[{"name":"to02"}]}},"bones":{"to02":{"scale":[{},{"time":0.5,"x":1.2,"y":1.2},{"time":2,"x":1.3,"y":1.3}]}}}}}